{
  "ЧУМА": "Plague",
  "СТРЕЛОК": "Deathslinger",
  "ТЕМНЫЙ ВЛАСТЕЛИН": "Dark Lord",
  "ТОРГОВКА ЧЕРЕПАМИ": "Skull Merchant",
  "КАННИБАЛ": "Cannibal",
  "ХОРОШИЙ ПАРЕНЬ": "Good Guy",
  "ЕГЕРЬ": "Houndmaster",
  "НАВЫК": "General Killer",
  "ОНРЁ": "Onryo",
  "ЛИЧ": "Lich",
  "ЛЕГИОН": "Legion",
  "СЛЭШЕР": "Slasher",
  "КРАСУ": "Krasue",
  "КСЕНОМОРФ": "Xenomorph",
  "МОР": "Blight",
  "ОНИ": "Oni",
  "ГУЛЬ": "Ghoul",
  "СВИНЬЯ": "Pig",
  "ДЕМОГОРГОН": "Demogorgon",
  "СИНГУЛЯРНОСТЬ": "Singularity",
  "ТРЮКАЧ": "Trickster",
  "ДЕРЕВЕНЩИНА": "Hillbilly",
  "ПРИЗРАК": "Wraith",
  "БЛИЗНЕЦЫ": "Twins",
  "ОХОТНИК": "Trapper",
  "МЕДСЕСТРА": "Nurse",
  "РЫЦАРЬ": "Knight",
  "НЕМЕЗИС": "Nemesis",
  "КЛОУН": "Clown",
  "КОШМАР": "Nightmare",
  "КУКЛОВОД": "Mastermind",
  "НЕВЕДОМОЕ": "Unknown",
  "ДУХ": "Spirit",
  "АНИМАТРОНИК": "Animatronic",
  "ТЕНЬ": "Shape",
  "СЕНОБИТ": "Cenobite",
  "ХУДОЖНИЦА": "Artist",
  "ДОКТОР": "Doctor",
  "ОХОТНИЦА": "Huntress",
  "ПЕРВЫЙ": "First",
  "ПАЛАЧ": "Executioner",
  "ГОУСТ ФЕЙС": "Ghostface",
  "ГРЯЗЬ": "Dredge",
  "ВЕДЬМА": "Hag"
}